[
  {
    "url": "http://files.remotecentral.com/library/3-1/apple/index.html",
    "title": "Apple",
    "count": 7,
    "level": 0,
    "sub": []
  },
  {
    "url": "http://files.remotecentral.com/library/3-1/arcam/index.html",
    "title": "Arcam",
    "count": 4,
    "level": 0,
    "sub": [
      {
        "url": "http://files.remotecentral.com/library/3-1/arcam/dvd_player/index.html",
        "title": "DVD Players",
        "count": 2,
        "level": 1,
        "sub": []
      },
      {
        "url": "http://files.remotecentral.com/library/3-1/arcam/receiver/index.html",
        "title": "Receivers",
        "count": 2,
        "level": 1,
        "sub": []
      }
    ]
  },
  {
    "url": "http://files.remotecentral.com/library/3-1/atlantic_technology/index.html",
    "title": "Atlantic Technology",
    "count": 19,
    "level": 0,
    "sub": [
      {
        "url": "http://files.remotecentral.com/library/3-1/atlantic_technology/powered_sound_bar/index.html",
        "title": "Powered Sound Bars",
        "count": 19,
        "level": 1,
        "sub": [
          {
            "url": "http://files.remotecentral.com/library/3-1/atlantic_technology/powered_sound_bar/audio_control/index.html",
            "title": "Audio Control",
            "count": 12,
            "level": 2
          },
          {
            "url": "http://files.remotecentral.com/library/3-1/atlantic_technology/powered_sound_bar/input_control/index.html",
            "title": "Input Control",
            "count": 5,
            "level": 2
          },
          {
            "url": "http://files.remotecentral.com/library/3-1/atlantic_technology/powered_sound_bar/power_control/index.html",
            "title": "Power Control",
            "count": 2,
            "level": 2
          }
        ]
      }
    ]
  },
  {
    "url": "http://files.remotecentral.com/library/3-1/auton/index.html",
    "title": "Auton",
    "count": 7,
    "level": 0,
    "sub": []
  },
  {
    "url": "http://files.remotecentral.com/library/3-1/beyonwiz/index.html",
    "title": "Beyonwiz",
    "count": 1,
    "level": 0,
    "sub": []
  },
  {
    "url": "http://files.remotecentral.com/library/3-1/chief_manufacturing/index.html",
    "title": "Chief Manufacturing",
    "count": 4,
    "level": 0,
    "sub": []
  },
  {
    "url": "http://files.remotecentral.com/library/3-1/definitive_technology/index.html",
    "title": "Definitive Technology",
    "count": 11,
    "level": 0,
    "sub": []
  },
  {
    "url": "http://files.remotecentral.com/library/3-1/denon/index.html",
    "title": "Denon",
    "count": 26,
    "level": 0,
    "sub": [
      {
        "url": "http://files.remotecentral.com/library/3-1/denon/cd_changer/index.html",
        "title": "CD Changers",
        "count": 2,
        "level": 1,
        "sub": []
      },
      {
        "url": "http://files.remotecentral.com/library/3-1/denon/dvd_player/index.html",
        "title": "DVD Players",
        "count": 2,
        "level": 1,
        "sub": []
      },
      {
        "url": "http://files.remotecentral.com/library/3-1/denon/ld_player/index.html",
        "title": "LD Players",
        "count": 2,
        "level": 1,
        "sub": []
      },
      {
        "url": "http://files.remotecentral.com/library/3-1/denon/receiver/index.html",
        "title": "Receivers",
        "count": 20,
        "level": 1,
        "sub": [
          {
            "url": "http://files.remotecentral.com/library/3-1/denon/receiver/others/index.html",
            "title": "Others",
            "count": 15,
            "level": 2
          },
          {
            "url": "http://files.remotecentral.com/library/3-1/denon/receiver/power_control/index.html",
            "title": "Power Control",
            "count": 2,
            "level": 2
          },
          {
            "url": "http://files.remotecentral.com/library/3-1/denon/receiver/speakers/index.html",
            "title": "Speakers",
            "count": 3,
            "level": 2
          }
        ]
      }
    ]
  },
  {
    "url": "http://files.remotecentral.com/library/3-1/directv/index.html",
    "title": "DirecTV",
    "count": 4,
    "level": 0,
    "sub": [
      {
        "url": "http://files.remotecentral.com/library/3-1/directv/dss_receiver/index.html",
        "title": "DSS Receivers",
        "count": 4,
        "level": 1,
        "sub": [
          {
            "url": "http://files.remotecentral.com/library/3-1/directv/dss_receiver/h20-100/index.html",
            "title": "H20-100",
            "count": 2,
            "level": 2
          },
          {
            "url": "http://files.remotecentral.com/library/3-1/directv/dss_receiver/r-15%252C_h23-600%252C_etc./index.html",
            "title": "R-15, H23-600, etc.",
            "count": 2,
            "level": 2
          }
        ]
      }
    ]
  },
  {
    "url": "http://files.remotecentral.com/library/3-1/dish_network/index.html",
    "title": "Dish Network",
    "count": 40,
    "level": 0,
    "sub": [
      {
        "url": "http://files.remotecentral.com/library/3-1/dish_network/dss_receiver/index.html",
        "title": "DSS Receivers",
        "count": 40,
        "level": 1,
        "sub": [
          {
            "url": "http://files.remotecentral.com/library/3-1/dish_network/dss_receiver/address_1/index.html",
            "title": "Address 1",
            "count": 2,
            "level": 2
          },
          {
            "url": "http://files.remotecentral.com/library/3-1/dish_network/dss_receiver/address_10/index.html",
            "title": "Address 10",
            "count": 2,
            "level": 2
          },
          {
            "url": "http://files.remotecentral.com/library/3-1/dish_network/dss_receiver/address_11/index.html",
            "title": "Address 11",
            "count": 2,
            "level": 2
          },
          {
            "url": "http://files.remotecentral.com/library/3-1/dish_network/dss_receiver/address_12/index.html",
            "title": "Address 12",
            "count": 2,
            "level": 2
          },
          {
            "url": "http://files.remotecentral.com/library/3-1/dish_network/dss_receiver/address_13/index.html",
            "title": "Address 13",
            "count": 2,
            "level": 2
          },
          {
            "url": "http://files.remotecentral.com/library/3-1/dish_network/dss_receiver/address_14/index.html",
            "title": "Address 14",
            "count": 2,
            "level": 2
          },
          {
            "url": "http://files.remotecentral.com/library/3-1/dish_network/dss_receiver/address_15/index.html",
            "title": "Address 15",
            "count": 2,
            "level": 2
          },
          {
            "url": "http://files.remotecentral.com/library/3-1/dish_network/dss_receiver/address_16/index.html",
            "title": "Address 16",
            "count": 2,
            "level": 2
          },
          {
            "url": "http://files.remotecentral.com/library/3-1/dish_network/dss_receiver/address_17/index.html",
            "title": "Address 17",
            "count": 2,
            "level": 2
          },
          {
            "url": "http://files.remotecentral.com/library/3-1/dish_network/dss_receiver/address_18/index.html",
            "title": "Address 18",
            "count": 2,
            "level": 2
          },
          {
            "url": "http://files.remotecentral.com/library/3-1/dish_network/dss_receiver/address_19/index.html",
            "title": "Address 19",
            "count": 2,
            "level": 2
          },
          {
            "url": "http://files.remotecentral.com/library/3-1/dish_network/dss_receiver/address_2/index.html",
            "title": "Address 2",
            "count": 2,
            "level": 2
          },
          {
            "url": "http://files.remotecentral.com/library/3-1/dish_network/dss_receiver/address_3/index.html",
            "title": "Address 3",
            "count": 2,
            "level": 2
          },
          {
            "url": "http://files.remotecentral.com/library/3-1/dish_network/dss_receiver/address_4/index.html",
            "title": "Address 4",
            "count": 2,
            "level": 2
          },
          {
            "url": "http://files.remotecentral.com/library/3-1/dish_network/dss_receiver/address_5/index.html",
            "title": "Address 5",
            "count": 2,
            "level": 2
          },
          {
            "url": "http://files.remotecentral.com/library/3-1/dish_network/dss_receiver/address_6/index.html",
            "title": "Address 6",
            "count": 2,
            "level": 2
          },
          {
            "url": "http://files.remotecentral.com/library/3-1/dish_network/dss_receiver/address_7/index.html",
            "title": "Address 7",
            "count": 2,
            "level": 2
          },
          {
            "url": "http://files.remotecentral.com/library/3-1/dish_network/dss_receiver/address_8/index.html",
            "title": "Address 8",
            "count": 2,
            "level": 2
          },
          {
            "url": "http://files.remotecentral.com/library/3-1/dish_network/dss_receiver/address_9/index.html",
            "title": "Address 9",
            "count": 2,
            "level": 2
          },
          {
            "url": "http://files.remotecentral.com/library/3-1/dish_network/dss_receiver/all_ir_addresses/index.html",
            "title": "All IR Addresses",
            "count": 2,
            "level": 2
          }
        ]
      }
    ]
  },
  {
    "url": "http://files.remotecentral.com/library/3-1/dream_multimedia/index.html",
    "title": "Dream Multimedia",
    "count": 8,
    "level": 0,
    "sub": []
  },
  {
    "url": "http://files.remotecentral.com/library/3-1/dvdo/index.html",
    "title": "DVDO",
    "count": 2,
    "level": 0,
    "sub": []
  },
  {
    "url": "http://files.remotecentral.com/library/3-1/enclave_audio/index.html",
    "title": "Enclave Audio",
    "count": 15,
    "level": 0,
    "sub": []
  },
  {
    "url": "http://files.remotecentral.com/library/3-1/force/index.html",
    "title": "Force",
    "count": 2,
    "level": 0,
    "sub": []
  },
  {
    "url": "http://files.remotecentral.com/library/3-1/fujitsu/index.html",
    "title": "Fujitsu",
    "count": 14,
    "level": 0,
    "sub": [
      {
        "url": "http://files.remotecentral.com/library/3-1/fujitsu/plasma_display/index.html",
        "title": "Plasma Displays",
        "count": 14,
        "level": 1,
        "sub": [
          {
            "url": "http://files.remotecentral.com/library/3-1/fujitsu/plasma_display/inputs/index.html",
            "title": "Inputs",
            "count": 6,
            "level": 2
          },
          {
            "url": "http://files.remotecentral.com/library/3-1/fujitsu/plasma_display/power_control/index.html",
            "title": "Power Control",
            "count": 2,
            "level": 2
          },
          {
            "url": "http://files.remotecentral.com/library/3-1/fujitsu/plasma_display/screen_formats/index.html",
            "title": "Screen Formats",
            "count": 6,
            "level": 2
          }
        ]
      }
    ]
  },
  {
    "url": "http://files.remotecentral.com/library/3-1/ge/index.html",
    "title": "GE",
    "count": 2,
    "level": 0,
    "sub": []
  },
  {
    "url": "http://files.remotecentral.com/library/3-1/gefen/index.html",
    "title": "Gefen",
    "count": 4,
    "level": 0,
    "sub": []
  },
  {
    "url": "http://files.remotecentral.com/library/3-1/grundig/index.html",
    "title": "Grundig",
    "count": 2,
    "level": 0,
    "sub": []
  },
  {
    "url": "http://files.remotecentral.com/library/3-1/harman__kardon/index.html",
    "title": "Harman/Kardon",
    "count": 11,
    "level": 0,
    "sub": [
      {
        "url": "http://files.remotecentral.com/library/3-1/harman__kardon/receiver/index.html",
        "title": "Receivers",
        "count": 11,
        "level": 1,
        "sub": [
          {
            "url": "http://files.remotecentral.com/library/3-1/harman__kardon/receiver/inputs/index.html",
            "title": "Inputs",
            "count": 9,
            "level": 2
          },
          {
            "url": "http://files.remotecentral.com/library/3-1/harman__kardon/receiver/power_control/index.html",
            "title": "Power Control",
            "count": 2,
            "level": 2
          }
        ]
      }
    ]
  },
  {
    "url": "http://files.remotecentral.com/library/3-1/hdi_dune/index.html",
    "title": "HDI Dune",
    "count": 2,
    "level": 0,
    "sub": []
  },
  {
    "url": "http://files.remotecentral.com/library/3-1/hitachi/index.html",
    "title": "Hitachi",
    "count": 12,
    "level": 0,
    "sub": [
      {
        "url": "http://files.remotecentral.com/library/3-1/hitachi/plasma_display/index.html",
        "title": "Plasma Displays",
        "count": 2,
        "level": 1,
        "sub": []
      },
      {
        "url": "http://files.remotecentral.com/library/3-1/hitachi/projector/index.html",
        "title": "Projectors",
        "count": 2,
        "level": 1,
        "sub": []
      },
      {
        "url": "http://files.remotecentral.com/library/3-1/hitachi/rp_television/index.html",
        "title": "RP Televisions",
        "count": 8,
        "level": 1,
        "sub": [
          {
            "url": "http://files.remotecentral.com/library/3-1/hitachi/rp_television/inputs/index.html",
            "title": "Inputs",
            "count": 6,
            "level": 2
          },
          {
            "url": "http://files.remotecentral.com/library/3-1/hitachi/rp_television/power_control/index.html",
            "title": "Power Control",
            "count": 2,
            "level": 2
          }
        ]
      }
    ]
  },
  {
    "url": "http://files.remotecentral.com/library/3-1/hp/index.html",
    "title": "HP",
    "count": 12,
    "level": 0,
    "sub": [
      {
        "url": "http://files.remotecentral.com/library/3-1/hp/television/index.html",
        "title": "Televisions",
        "count": 12,
        "level": 1,
        "sub": [
          {
            "url": "http://files.remotecentral.com/library/3-1/hp/television/inputs/index.html",
            "title": "Inputs",
            "count": 10,
            "level": 2
          },
          {
            "url": "http://files.remotecentral.com/library/3-1/hp/television/power_control/index.html",
            "title": "Power Control",
            "count": 2,
            "level": 2
          }
        ]
      }
    ]
  },
  {
    "url": "http://files.remotecentral.com/library/3-1/hughes/index.html",
    "title": "Hughes",
    "count": 4,
    "level": 0,
    "sub": []
  },
  {
    "url": "http://files.remotecentral.com/library/3-1/humax/index.html",
    "title": "Humax",
    "count": 6,
    "level": 0,
    "sub": [
      {
        "url": "http://files.remotecentral.com/library/3-1/humax/dvr/index.html",
        "title": "DVRs",
        "count": 6,
        "level": 1,
        "sub": [
          {
            "url": "http://files.remotecentral.com/library/3-1/humax/dvr/hdr-7500t/index.html",
            "title": "HDR-7500T",
            "count": 2,
            "level": 2
          },
          {
            "url": "http://files.remotecentral.com/library/3-1/humax/dvr/power_control/index.html",
            "title": "Power Control",
            "count": 4,
            "level": 2
          }
        ]
      }
    ]
  },
  {
    "url": "http://files.remotecentral.com/library/3-1/infocus/index.html",
    "title": "Infocus",
    "count": 24,
    "level": 0,
    "sub": [
      {
        "url": "http://files.remotecentral.com/library/3-1/infocus/projector/index.html",
        "title": "Projectors",
        "count": 24,
        "level": 1,
        "sub": [
          {
            "url": "http://files.remotecentral.com/library/3-1/infocus/projector/5700__7200/index.html",
            "title": "5700/7200",
            "count": 2,
            "level": 2
          },
          {
            "url": "http://files.remotecentral.com/library/3-1/infocus/projector/generic/index.html",
            "title": "Generic",
            "count": 2,
            "level": 2
          },
          {
            "url": "http://files.remotecentral.com/library/3-1/infocus/projector/lp540__lp640/index.html",
            "title": "LP540/LP640",
            "count": 20,
            "level": 2
          }
        ]
      }
    ]
  },
  {
    "url": "http://files.remotecentral.com/library/3-1/jvc/index.html",
    "title": "JVC",
    "count": 36,
    "level": 0,
    "sub": [
      {
        "url": "http://files.remotecentral.com/library/3-1/jvc/projector/index.html",
        "title": "Projectors",
        "count": 10,
        "level": 1,
        "sub": [
          {
            "url": "http://files.remotecentral.com/library/3-1/jvc/projector/inputs/index.html",
            "title": "Inputs",
            "count": 8,
            "level": 2
          },
          {
            "url": "http://files.remotecentral.com/library/3-1/jvc/projector/power_control/index.html",
            "title": "Power Control",
            "count": 2,
            "level": 2
          }
        ]
      },
      {
        "url": "http://files.remotecentral.com/library/3-1/jvc/receiver/index.html",
        "title": "Receivers",
        "count": 2,
        "level": 1,
        "sub": []
      },
      {
        "url": "http://files.remotecentral.com/library/3-1/jvc/television/index.html",
        "title": "Televisions",
        "count": 10,
        "level": 1,
        "sub": [
          {
            "url": "http://files.remotecentral.com/library/3-1/jvc/television/inputs/index.html",
            "title": "Inputs",
            "count": 4,
            "level": 2
          },
          {
            "url": "http://files.remotecentral.com/library/3-1/jvc/television/power_control/index.html",
            "title": "Power Control",
            "count": 3,
            "level": 2
          },
          {
            "url": "http://files.remotecentral.com/library/3-1/jvc/television/screen_formats/index.html",
            "title": "Screen Formats",
            "count": 3,
            "level": 2
          }
        ]
      },
      {
        "url": "http://files.remotecentral.com/library/3-1/jvc/vcr/index.html",
        "title": "VCRs",
        "count": 14,
        "level": 1,
        "sub": [
          {
            "url": "http://files.remotecentral.com/library/3-1/jvc/vcr/code_a/index.html",
            "title": "Code A",
            "count": 9,
            "level": 2
          },
          {
            "url": "http://files.remotecentral.com/library/3-1/jvc/vcr/code_b/index.html",
            "title": "Code B",
            "count": 5,
            "level": 2
          }
        ]
      }
    ]
  },
  {
    "url": "http://files.remotecentral.com/library/3-1/kenwood/index.html",
    "title": "Kenwood",
    "count": 9,
    "level": 0,
    "sub": [
      {
        "url": "http://files.remotecentral.com/library/3-1/kenwood/dvd_changer/index.html",
        "title": "DVD Changers",
        "count": 2,
        "level": 1,
        "sub": []
      },
      {
        "url": "http://files.remotecentral.com/library/3-1/kenwood/receiver/index.html",
        "title": "Receivers",
        "count": 7,
        "level": 1,
        "sub": []
      }
    ]
  },
  {
    "url": "http://files.remotecentral.com/library/3-1/lg/index.html",
    "title": "LG",
    "count": 18,
    "level": 0,
    "sub": [
      {
        "url": "http://files.remotecentral.com/library/3-1/lg/2008_television/index.html",
        "title": "2008 Televisions",
        "count": 15,
        "level": 1,
        "sub": [
          {
            "url": "http://files.remotecentral.com/library/3-1/lg/2008_television/inputs/index.html",
            "title": "Inputs",
            "count": 10,
            "level": 2
          },
          {
            "url": "http://files.remotecentral.com/library/3-1/lg/2008_television/power_control/index.html",
            "title": "Power Control",
            "count": 2,
            "level": 2
          },
          {
            "url": "http://files.remotecentral.com/library/3-1/lg/2008_television/screen_formats/index.html",
            "title": "Screen Formats",
            "count": 3,
            "level": 2
          }
        ]
      },
      {
        "url": "http://files.remotecentral.com/library/3-1/lg/blu-ray_disc_player/index.html",
        "title": "Blu-ray Disc Players",
        "count": 3,
        "level": 1,
        "sub": []
      }
    ]
  },
  {
    "url": "http://files.remotecentral.com/library/3-1/loewe/index.html",
    "title": "Loewe",
    "count": 20,
    "level": 0,
    "sub": [
      {
        "url": "http://files.remotecentral.com/library/3-1/loewe/television/index.html",
        "title": "Televisions",
        "count": 20,
        "level": 1,
        "sub": [
          {
            "url": "http://files.remotecentral.com/library/3-1/loewe/television/l2650_chassis/index.html",
            "title": "L2650 Chassis",
            "count": 9,
            "level": 2
          },
          {
            "url": "http://files.remotecentral.com/library/3-1/loewe/television/l2710_chassis/index.html",
            "title": "L2710 Chassis",
            "count": 10,
            "level": 2
          },
          {
            "url": "http://files.remotecentral.com/library/3-1/loewe/television/q2500_chassis/index.html",
            "title": "Q2500 Chassis",
            "count": 1,
            "level": 2
          }
        ]
      }
    ]
  },
  {
    "url": "http://files.remotecentral.com/library/3-1/logik/index.html",
    "title": "Logik",
    "count": 10,
    "level": 0,
    "sub": [
      {
        "url": "http://files.remotecentral.com/library/3-1/logik/television/index.html",
        "title": "Televisions",
        "count": 10,
        "level": 1,
        "sub": [
          {
            "url": "http://files.remotecentral.com/library/3-1/logik/television/input_control/index.html",
            "title": "Input Control",
            "count": 8,
            "level": 2
          },
          {
            "url": "http://files.remotecentral.com/library/3-1/logik/television/power_control/index.html",
            "title": "Power Control",
            "count": 2,
            "level": 2
          }
        ]
      }
    ]
  },
  {
    "url": "http://files.remotecentral.com/library/3-1/marantz/index.html",
    "title": "Marantz",
    "count": 14,
    "level": 0,
    "sub": [
      {
        "url": "http://files.remotecentral.com/library/3-1/marantz/dvd_changer/index.html",
        "title": "DVD Changers",
        "count": 2,
        "level": 1,
        "sub": []
      },
      {
        "url": "http://files.remotecentral.com/library/3-1/marantz/dvd_player/index.html",
        "title": "DVD Players",
        "count": 2,
        "level": 1,
        "sub": []
      },
      {
        "url": "http://files.remotecentral.com/library/3-1/marantz/preamplifier/index.html",
        "title": "Preamplifiers",
        "count": 8,
        "level": 1,
        "sub": [
          {
            "url": "http://files.remotecentral.com/library/3-1/marantz/preamplifier/inputs/index.html",
            "title": "Inputs",
            "count": 4,
            "level": 2
          },
          {
            "url": "http://files.remotecentral.com/library/3-1/marantz/preamplifier/other/index.html",
            "title": "Other",
            "count": 2,
            "level": 2
          },
          {
            "url": "http://files.remotecentral.com/library/3-1/marantz/preamplifier/power_control/index.html",
            "title": "Power Control",
            "count": 2,
            "level": 2
          }
        ]
      },
      {
        "url": "http://files.remotecentral.com/library/3-1/marantz/tuner/index.html",
        "title": "Tuners",
        "count": 2,
        "level": 1,
        "sub": []
      }
    ]
  },
  {
    "url": "http://files.remotecentral.com/library/3-1/mcintosh/index.html",
    "title": "McIntosh",
    "count": 2,
    "level": 0,
    "sub": []
  },
  {
    "url": "http://files.remotecentral.com/library/3-1/metz/index.html",
    "title": "Metz",
    "count": 2,
    "level": 0,
    "sub": []
  },
  {
    "url": "http://files.remotecentral.com/library/3-1/microsoft/index.html",
    "title": "Microsoft",
    "count": 31,
    "level": 0,
    "sub": [
      {
        "url": "http://files.remotecentral.com/library/3-1/microsoft/game_console/index.html",
        "title": "Game Consoles",
        "count": 2,
        "level": 1,
        "sub": []
      },
      {
        "url": "http://files.remotecentral.com/library/3-1/microsoft/windows_media_center/index.html",
        "title": "Windows Media Centers",
        "count": 29,
        "level": 1,
        "sub": []
      }
    ]
  },
  {
    "url": "http://files.remotecentral.com/library/3-1/mitsubishi/index.html",
    "title": "Mitsubishi",
    "count": 41,
    "level": 0,
    "sub": [
      {
        "url": "http://files.remotecentral.com/library/3-1/mitsubishi/dss_receiver/index.html",
        "title": "DSS Receivers",
        "count": 2,
        "level": 1,
        "sub": []
      },
      {
        "url": "http://files.remotecentral.com/library/3-1/mitsubishi/rp_television/index.html",
        "title": "RP Televisions",
        "count": 16,
        "level": 1,
        "sub": [
          {
            "url": "http://files.remotecentral.com/library/3-1/mitsubishi/rp_television/inputs/index.html",
            "title": "Inputs",
            "count": 13,
            "level": 2
          },
          {
            "url": "http://files.remotecentral.com/library/3-1/mitsubishi/rp_television/other/index.html",
            "title": "Other",
            "count": 1,
            "level": 2
          },
          {
            "url": "http://files.remotecentral.com/library/3-1/mitsubishi/rp_television/power_control/index.html",
            "title": "Power Control",
            "count": 2,
            "level": 2
          }
        ]
      },
      {
        "url": "http://files.remotecentral.com/library/3-1/mitsubishi/television/index.html",
        "title": "Televisions",
        "count": 13,
        "level": 1,
        "sub": [
          {
            "url": "http://files.remotecentral.com/library/3-1/mitsubishi/television/inputs/index.html",
            "title": "Inputs",
            "count": 9,
            "level": 2
          },
          {
            "url": "http://files.remotecentral.com/library/3-1/mitsubishi/television/power_control/index.html",
            "title": "Power Control",
            "count": 4,
            "level": 2
          }
        ]
      },
      {
        "url": "http://files.remotecentral.com/library/3-1/mitsubishi/vcr/index.html",
        "title": "VCRs",
        "count": 10,
        "level": 1,
        "sub": [
          {
            "url": "http://files.remotecentral.com/library/3-1/mitsubishi/vcr/code_a/index.html",
            "title": "Code A",
            "count": 5,
            "level": 2
          },
          {
            "url": "http://files.remotecentral.com/library/3-1/mitsubishi/vcr/code_b/index.html",
            "title": "Code B",
            "count": 5,
            "level": 2
          }
        ]
      }
    ]
  },
  {
    "url": "http://files.remotecentral.com/library/3-1/nad/index.html",
    "title": "NAD",
    "count": 4,
    "level": 0,
    "sub": [
      {
        "url": "http://files.remotecentral.com/library/3-1/nad/receiver/index.html",
        "title": "Receivers",
        "count": 2,
        "level": 1,
        "sub": []
      },
      {
        "url": "http://files.remotecentral.com/library/3-1/nad/whole_system/index.html",
        "title": "Whole Systems",
        "count": 2,
        "level": 1,
        "sub": []
      }
    ]
  },
  {
    "url": "http://files.remotecentral.com/library/3-1/nec/index.html",
    "title": "NEC",
    "count": 10,
    "level": 0,
    "sub": [
      {
        "url": "http://files.remotecentral.com/library/3-1/nec/plasma_display/index.html",
        "title": "Plasma Displays",
        "count": 10,
        "level": 1,
        "sub": [
          {
            "url": "http://files.remotecentral.com/library/3-1/nec/plasma_display/input_control/index.html",
            "title": "Input Control",
            "count": 8,
            "level": 2
          },
          {
            "url": "http://files.remotecentral.com/library/3-1/nec/plasma_display/power_control/index.html",
            "title": "Power Control",
            "count": 2,
            "level": 2
          }
        ]
      }
    ]
  },
  {
    "url": "http://files.remotecentral.com/library/3-1/netgear/index.html",
    "title": "Netgear",
    "count": 2,
    "level": 0,
    "sub": []
  },
  {
    "url": "http://files.remotecentral.com/library/3-1/onkyo/index.html",
    "title": "Onkyo",
    "count": 28,
    "level": 0,
    "sub": [
      {
        "url": "http://files.remotecentral.com/library/3-1/onkyo/cd_player/index.html",
        "title": "CD Players",
        "count": 2,
        "level": 1,
        "sub": []
      },
      {
        "url": "http://files.remotecentral.com/library/3-1/onkyo/dvd_player/index.html",
        "title": "DVD Players",
        "count": 10,
        "level": 1,
        "sub": [
          {
            "url": "http://files.remotecentral.com/library/3-1/onkyo/dvd_player/disc_control/index.html",
            "title": "Disc Control",
            "count": 8,
            "level": 2
          },
          {
            "url": "http://files.remotecentral.com/library/3-1/onkyo/dvd_player/power_control/index.html",
            "title": "Power Control",
            "count": 2,
            "level": 2
          }
        ]
      },
      {
        "url": "http://files.remotecentral.com/library/3-1/onkyo/receiver/index.html",
        "title": "Receivers",
        "count": 16,
        "level": 1,
        "sub": [
          {
            "url": "http://files.remotecentral.com/library/3-1/onkyo/receiver/inputs/index.html",
            "title": "Inputs",
            "count": 11,
            "level": 2
          },
          {
            "url": "http://files.remotecentral.com/library/3-1/onkyo/receiver/other/index.html",
            "title": "Other",
            "count": 3,
            "level": 2
          },
          {
            "url": "http://files.remotecentral.com/library/3-1/onkyo/receiver/power_control/index.html",
            "title": "Power Control",
            "count": 2,
            "level": 2
          }
        ]
      }
    ]
  },
  {
    "url": "http://files.remotecentral.com/library/3-1/oppo_digital/index.html",
    "title": "Oppo Digital",
    "count": 2,
    "level": 0,
    "sub": []
  },
  {
    "url": "http://files.remotecentral.com/library/3-1/outlaw/index.html",
    "title": "Outlaw",
    "count": 2,
    "level": 0,
    "sub": []
  },
  {
    "url": "http://files.remotecentral.com/library/3-1/panasonic/index.html",
    "title": "Panasonic",
    "count": 85,
    "level": 0,
    "sub": [
      {
        "url": "http://files.remotecentral.com/library/3-1/panasonic/dvd_player/index.html",
        "title": "DVD Players",
        "count": 8,
        "level": 1,
        "sub": [
          {
            "url": "http://files.remotecentral.com/library/3-1/panasonic/dvd_player/set_1/index.html",
            "title": "Set 1",
            "count": 4,
            "level": 2
          },
          {
            "url": "http://files.remotecentral.com/library/3-1/panasonic/dvd_player/set_2/index.html",
            "title": "Set 2",
            "count": 4,
            "level": 2
          }
        ]
      },
      {
        "url": "http://files.remotecentral.com/library/3-1/panasonic/dvd_recorder/index.html",
        "title": "DVD Recorders",
        "count": 27,
        "level": 1,
        "sub": [
          {
            "url": "http://files.remotecentral.com/library/3-1/panasonic/dvd_recorder/code_1/index.html",
            "title": "Code 1",
            "count": 3,
            "level": 2
          },
          {
            "url": "http://files.remotecentral.com/library/3-1/panasonic/dvd_recorder/code_2/index.html",
            "title": "Code 2",
            "count": 3,
            "level": 2
          },
          {
            "url": "http://files.remotecentral.com/library/3-1/panasonic/dvd_recorder/code_3/index.html",
            "title": "Code 3",
            "count": 6,
            "level": 2
          },
          {
            "url": "http://files.remotecentral.com/library/3-1/panasonic/dvd_recorder/code_4/index.html",
            "title": "Code 4",
            "count": 5,
            "level": 2
          },
          {
            "url": "http://files.remotecentral.com/library/3-1/panasonic/dvd_recorder/code_5/index.html",
            "title": "Code 5",
            "count": 5,
            "level": 2
          },
          {
            "url": "http://files.remotecentral.com/library/3-1/panasonic/dvd_recorder/code_6/index.html",
            "title": "Code 6",
            "count": 5,
            "level": 2
          }
        ]
      },
      {
        "url": "http://files.remotecentral.com/library/3-1/panasonic/dvd__hdd_recorder/index.html",
        "title": "DVD/HDD Recorders",
        "count": 2,
        "level": 1,
        "sub": []
      },
      {
        "url": "http://files.remotecentral.com/library/3-1/panasonic/dvd__vcr_combo/index.html",
        "title": "DVD/VCR Combos",
        "count": 1,
        "level": 1,
        "sub": []
      },
      {
        "url": "http://files.remotecentral.com/library/3-1/panasonic/hdtv/index.html",
        "title": "HDTVs",
        "count": 7,
        "level": 1,
        "sub": [
          {
            "url": "http://files.remotecentral.com/library/3-1/panasonic/hdtv/inputs/index.html",
            "title": "Inputs",
            "count": 5,
            "level": 2
          },
          {
            "url": "http://files.remotecentral.com/library/3-1/panasonic/hdtv/power_control/index.html",
            "title": "Power Control",
            "count": 2,
            "level": 2
          }
        ]
      },
      {
        "url": "http://files.remotecentral.com/library/3-1/panasonic/plasma_display/index.html",
        "title": "Plasma Displays",
        "count": 13,
        "level": 1,
        "sub": [
          {
            "url": "http://files.remotecentral.com/library/3-1/panasonic/plasma_display/inputs/index.html",
            "title": "Inputs",
            "count": 6,
            "level": 2
          },
          {
            "url": "http://files.remotecentral.com/library/3-1/panasonic/plasma_display/power_control/index.html",
            "title": "Power Control",
            "count": 2,
            "level": 2
          },
          {
            "url": "http://files.remotecentral.com/library/3-1/panasonic/plasma_display/screen_formats/index.html",
            "title": "Screen Formats",
            "count": 5,
            "level": 2
          }
        ]
      },
      {
        "url": "http://files.remotecentral.com/library/3-1/panasonic/projector/index.html",
        "title": "Projectors",
        "count": 2,
        "level": 1,
        "sub": []
      },
      {
        "url": "http://files.remotecentral.com/library/3-1/panasonic/receiver/index.html",
        "title": "Receivers",
        "count": 2,
        "level": 1,
        "sub": []
      },
      {
        "url": "http://files.remotecentral.com/library/3-1/panasonic/television/index.html",
        "title": "Televisions",
        "count": 12,
        "level": 1,
        "sub": [
          {
            "url": "http://files.remotecentral.com/library/3-1/panasonic/television/inputs/index.html",
            "title": "Inputs",
            "count": 8,
            "level": 2
          },
          {
            "url": "http://files.remotecentral.com/library/3-1/panasonic/television/power_control/index.html",
            "title": "Power Control",
            "count": 4,
            "level": 2
          }
        ]
      },
      {
        "url": "http://files.remotecentral.com/library/3-1/panasonic/vcr/index.html",
        "title": "VCRs",
        "count": 11,
        "level": 1,
        "sub": [
          {
            "url": "http://files.remotecentral.com/library/3-1/panasonic/vcr/inputs/index.html",
            "title": "Inputs",
            "count": 5,
            "level": 2
          },
          {
            "url": "http://files.remotecentral.com/library/3-1/panasonic/vcr/other/index.html",
            "title": "Other",
            "count": 2,
            "level": 2
          },
          {
            "url": "http://files.remotecentral.com/library/3-1/panasonic/vcr/power_control/index.html",
            "title": "Power Control",
            "count": 3,
            "level": 2
          },
          {
            "url": "http://files.remotecentral.com/library/3-1/panasonic/vcr/vcr_2/index.html",
            "title": "VCR 2",
            "count": 1,
            "level": 2
          }
        ]
      }
    ]
  },
  {
    "url": "http://files.remotecentral.com/library/3-1/pentax/index.html",
    "title": "Pentax",
    "count": 2,
    "level": 0,
    "sub": []
  },
  {
    "url": "http://files.remotecentral.com/library/3-1/philips/index.html",
    "title": "Philips",
    "count": 12,
    "level": 0,
    "sub": [
      {
        "url": "http://files.remotecentral.com/library/3-1/philips/lcd_television/index.html",
        "title": "LCD Televisions",
        "count": 10,
        "level": 1,
        "sub": [
          {
            "url": "http://files.remotecentral.com/library/3-1/philips/lcd_television/full_hex/index.html",
            "title": "Full Hex",
            "count": 2,
            "level": 2
          },
          {
            "url": "http://files.remotecentral.com/library/3-1/philips/lcd_television/inputs/index.html",
            "title": "Inputs",
            "count": 6,
            "level": 2
          },
          {
            "url": "http://files.remotecentral.com/library/3-1/philips/lcd_television/power_control/index.html",
            "title": "Power Control",
            "count": 2,
            "level": 2
          }
        ]
      },
      {
        "url": "http://files.remotecentral.com/library/3-1/philips/streamium/index.html",
        "title": "Streamiums",
        "count": 2,
        "level": 1,
        "sub": []
      }
    ]
  },
  {
    "url": "http://files.remotecentral.com/library/3-1/pinnacle_systems/index.html",
    "title": "Pinnacle Systems",
    "count": 1,
    "level": 0,
    "sub": []
  },
  {
    "url": "http://files.remotecentral.com/library/3-1/pioneer/index.html",
    "title": "Pioneer",
    "count": 60,
    "level": 0,
    "sub": [
      {
        "url": "http://files.remotecentral.com/library/3-1/pioneer/cd_jukebox/index.html",
        "title": "CD Jukeboxes",
        "count": 2,
        "level": 1,
        "sub": []
      },
      {
        "url": "http://files.remotecentral.com/library/3-1/pioneer/dvd_player/index.html",
        "title": "DVD Players",
        "count": 2,
        "level": 1,
        "sub": []
      },
      {
        "url": "http://files.remotecentral.com/library/3-1/pioneer/dvd_recorder/index.html",
        "title": "DVD Recorders",
        "count": 2,
        "level": 1,
        "sub": []
      },
      {
        "url": "http://files.remotecentral.com/library/3-1/pioneer/dvd__ld_player/index.html",
        "title": "DVD/LD Players",
        "count": 2,
        "level": 1,
        "sub": []
      },
      {
        "url": "http://files.remotecentral.com/library/3-1/pioneer/ld_player/index.html",
        "title": "LD Players",
        "count": 2,
        "level": 1,
        "sub": []
      },
      {
        "url": "http://files.remotecentral.com/library/3-1/pioneer/plasma_display/index.html",
        "title": "Plasma Displays",
        "count": 6,
        "level": 1,
        "sub": [
          {
            "url": "http://files.remotecentral.com/library/3-1/pioneer/plasma_display/inputs/index.html",
            "title": "Inputs",
            "count": 4,
            "level": 2
          },
          {
            "url": "http://files.remotecentral.com/library/3-1/pioneer/plasma_display/power_control/index.html",
            "title": "Power Control",
            "count": 2,
            "level": 2
          }
        ]
      },
      {
        "url": "http://files.remotecentral.com/library/3-1/pioneer/receiver/index.html",
        "title": "Receivers",
        "count": 34,
        "level": 1,
        "sub": [
          {
            "url": "http://files.remotecentral.com/library/3-1/pioneer/receiver/inputs/index.html",
            "title": "Inputs",
            "count": 9,
            "level": 2
          },
          {
            "url": "http://files.remotecentral.com/library/3-1/pioneer/receiver/power_%2526_inputs/index.html",
            "title": "Power & Inputs",
            "count": 6,
            "level": 2
          },
          {
            "url": "http://files.remotecentral.com/library/3-1/pioneer/receiver/power_control/index.html",
            "title": "Power Control",
            "count": 2,
            "level": 2
          },
          {
            "url": "http://files.remotecentral.com/library/3-1/pioneer/receiver/sound_control/index.html",
            "title": "Sound Control",
            "count": 3,
            "level": 2
          },
          {
            "url": "http://files.remotecentral.com/library/3-1/pioneer/receiver/speakers/index.html",
            "title": "Speakers",
            "count": 4,
            "level": 2
          },
          {
            "url": "http://files.remotecentral.com/library/3-1/pioneer/receiver/zone_2/index.html",
            "title": "Zone 2",
            "count": 3,
            "level": 2
          },
          {
            "url": "http://files.remotecentral.com/library/3-1/pioneer/receiver/zone_2_inputs/index.html",
            "title": "Zone 2 Inputs",
            "count": 7,
            "level": 2
          }
        ]
      },
      {
        "url": "http://files.remotecentral.com/library/3-1/pioneer/rp_television/index.html",
        "title": "RP Televisions",
        "count": 8,
        "level": 1,
        "sub": [
          {
            "url": "http://files.remotecentral.com/library/3-1/pioneer/rp_television/inputs/index.html",
            "title": "Inputs",
            "count": 4,
            "level": 2
          },
          {
            "url": "http://files.remotecentral.com/library/3-1/pioneer/rp_television/power_control_%25231/index.html",
            "title": "Power Control #1",
            "count": 2,
            "level": 2
          },
          {
            "url": "http://files.remotecentral.com/library/3-1/pioneer/rp_television/power_control_%25232/index.html",
            "title": "Power Control #2",
            "count": 2,
            "level": 2
          }
        ]
      },
      {
        "url": "http://files.remotecentral.com/library/3-1/pioneer/tape_deck/index.html",
        "title": "Tape Decks",
        "count": 2,
        "level": 1,
        "sub": []
      }
    ]
  },
  {
    "url": "http://files.remotecentral.com/library/3-1/proscan/index.html",
    "title": "Proscan",
    "count": 4,
    "level": 0,
    "sub": [
      {
        "url": "http://files.remotecentral.com/library/3-1/proscan/dvd_player/index.html",
        "title": "DVD Players",
        "count": 2,
        "level": 1,
        "sub": []
      },
      {
        "url": "http://files.remotecentral.com/library/3-1/proscan/television/index.html",
        "title": "Televisions",
        "count": 2,
        "level": 1,
        "sub": []
      }
    ]
  },
  {
    "url": "http://files.remotecentral.com/library/3-1/rca/index.html",
    "title": "RCA",
    "count": 39,
    "level": 0,
    "sub": [
      {
        "url": "http://files.remotecentral.com/library/3-1/rca/dss_receiver/index.html",
        "title": "DSS Receivers",
        "count": 2,
        "level": 1,
        "sub": []
      },
      {
        "url": "http://files.remotecentral.com/library/3-1/rca/dvd_player/index.html",
        "title": "DVD Players",
        "count": 2,
        "level": 1,
        "sub": []
      },
      {
        "url": "http://files.remotecentral.com/library/3-1/rca/hdtv_receiver/index.html",
        "title": "HDTV Receivers",
        "count": 19,
        "level": 1,
        "sub": [
          {
            "url": "http://files.remotecentral.com/library/3-1/rca/hdtv_receiver/inputs/index.html",
            "title": "Inputs",
            "count": 4,
            "level": 2
          },
          {
            "url": "http://files.remotecentral.com/library/3-1/rca/hdtv_receiver/other/index.html",
            "title": "Other",
            "count": 8,
            "level": 2
          },
          {
            "url": "http://files.remotecentral.com/library/3-1/rca/hdtv_receiver/power_control/index.html",
            "title": "Power Control",
            "count": 2,
            "level": 2
          },
          {
            "url": "http://files.remotecentral.com/library/3-1/rca/hdtv_receiver/screen_formats/index.html",
            "title": "Screen Formats",
            "count": 5,
            "level": 2
          }
        ]
      },
      {
        "url": "http://files.remotecentral.com/library/3-1/rca/television/index.html",
        "title": "Televisions",
        "count": 14,
        "level": 1,
        "sub": [
          {
            "url": "http://files.remotecentral.com/library/3-1/rca/television/power_control/index.html",
            "title": "Power Control",
            "count": 2,
            "level": 2
          },
          {
            "url": "http://files.remotecentral.com/library/3-1/rca/television/scenium_models/index.html",
            "title": "Scenium Models",
            "count": 12,
            "level": 2
          }
        ]
      },
      {
        "url": "http://files.remotecentral.com/library/3-1/rca/vcr/index.html",
        "title": "VCRs",
        "count": 2,
        "level": 1,
        "sub": []
      }
    ]
  },
  {
    "url": "http://files.remotecentral.com/library/3-1/replaytv/index.html",
    "title": "ReplayTV",
    "count": 2,
    "level": 0,
    "sub": []
  },
  {
    "url": "http://files.remotecentral.com/library/3-1/roku_labs/index.html",
    "title": "Roku Labs",
    "count": 39,
    "level": 0,
    "sub": [
      {
        "url": "http://files.remotecentral.com/library/3-1/roku_labs/media_player/index.html",
        "title": "Media Players",
        "count": 39,
        "level": 1,
        "sub": [
          {
            "url": "http://files.remotecentral.com/library/3-1/roku_labs/media_player/2016_models/index.html",
            "title": "2016 Models",
            "count": 15,
            "level": 2
          },
          {
            "url": "http://files.remotecentral.com/library/3-1/roku_labs/media_player/2016_models_-_services/index.html",
            "title": "2016 Models - Services",
            "count": 20,
            "level": 2
          },
          {
            "url": "http://files.remotecentral.com/library/3-1/roku_labs/media_player/photobridge/index.html",
            "title": "PhotoBridge",
            "count": 2,
            "level": 2
          },
          {
            "url": "http://files.remotecentral.com/library/3-1/roku_labs/media_player/soundbridge/index.html",
            "title": "SoundBridge",
            "count": 2,
            "level": 2
          }
        ]
      }
    ]
  },
  {
    "url": "http://files.remotecentral.com/library/3-1/rotel/index.html",
    "title": "Rotel",
    "count": 2,
    "level": 0,
    "sub": []
  },
  {
    "url": "http://files.remotecentral.com/library/3-1/runco/index.html",
    "title": "Runco",
    "count": 30,
    "level": 0,
    "sub": [
      {
        "url": "http://files.remotecentral.com/library/3-1/runco/projector/index.html",
        "title": "Projectors",
        "count": 30,
        "level": 1,
        "sub": [
          {
            "url": "http://files.remotecentral.com/library/3-1/runco/projector/general/index.html",
            "title": "General",
            "count": 9,
            "level": 2
          },
          {
            "url": "http://files.remotecentral.com/library/3-1/runco/projector/input_control/index.html",
            "title": "Input Control",
            "count": 5,
            "level": 2
          },
          {
            "url": "http://files.remotecentral.com/library/3-1/runco/projector/picture_control/index.html",
            "title": "Picture Control",
            "count": 14,
            "level": 2
          },
          {
            "url": "http://files.remotecentral.com/library/3-1/runco/projector/power_control/index.html",
            "title": "Power Control",
            "count": 2,
            "level": 2
          }
        ]
      }
    ]
  },
  {
    "url": "http://files.remotecentral.com/library/3-1/sampo/index.html",
    "title": "Sampo",
    "count": 9,
    "level": 0,
    "sub": [
      {
        "url": "http://files.remotecentral.com/library/3-1/sampo/hdtv/index.html",
        "title": "HDTVs",
        "count": 9,
        "level": 1,
        "sub": [
          {
            "url": "http://files.remotecentral.com/library/3-1/sampo/hdtv/inputs/index.html",
            "title": "Inputs",
            "count": 6,
            "level": 2
          },
          {
            "url": "http://files.remotecentral.com/library/3-1/sampo/hdtv/other/index.html",
            "title": "Other",
            "count": 1,
            "level": 2
          },
          {
            "url": "http://files.remotecentral.com/library/3-1/sampo/hdtv/power_control/index.html",
            "title": "Power Control",
            "count": 2,
            "level": 2
          }
        ]
      }
    ]
  },
  {
    "url": "http://files.remotecentral.com/library/3-1/samsung/index.html",
    "title": "Samsung",
    "count": 83,
    "level": 0,
    "sub": [
      {
        "url": "http://files.remotecentral.com/library/3-1/samsung/hdtv_television/index.html",
        "title": "HDTV Televisions",
        "count": 4,
        "level": 1,
        "sub": []
      },
      {
        "url": "http://files.remotecentral.com/library/3-1/samsung/hln_series_hdtv/index.html",
        "title": "HLN Series HDTVs",
        "count": 14,
        "level": 1,
        "sub": [
          {
            "url": "http://files.remotecentral.com/library/3-1/samsung/hln_series_hdtv/inputs/index.html",
            "title": "Inputs",
            "count": 12,
            "level": 2
          },
          {
            "url": "http://files.remotecentral.com/library/3-1/samsung/hln_series_hdtv/power_control/index.html",
            "title": "Power Control",
            "count": 2,
            "level": 2
          }
        ]
      },
      {
        "url": "http://files.remotecentral.com/library/3-1/samsung/hlp_series_hdtv/index.html",
        "title": "HLP Series HDTVs",
        "count": 14,
        "level": 1,
        "sub": [
          {
            "url": "http://files.remotecentral.com/library/3-1/samsung/hlp_series_hdtv/inputs/index.html",
            "title": "Inputs",
            "count": 12,
            "level": 2
          },
          {
            "url": "http://files.remotecentral.com/library/3-1/samsung/hlp_series_hdtv/power_control/index.html",
            "title": "Power Control",
            "count": 2,
            "level": 2
          }
        ]
      },
      {
        "url": "http://files.remotecentral.com/library/3-1/samsung/hlr_series_hdtv/index.html",
        "title": "HLR Series HDTVs",
        "count": 9,
        "level": 1,
        "sub": [
          {
            "url": "http://files.remotecentral.com/library/3-1/samsung/hlr_series_hdtv/inputs/index.html",
            "title": "Inputs",
            "count": 7,
            "level": 2
          },
          {
            "url": "http://files.remotecentral.com/library/3-1/samsung/hlr_series_hdtv/power_control/index.html",
            "title": "Power Control",
            "count": 2,
            "level": 2
          }
        ]
      },
      {
        "url": "http://files.remotecentral.com/library/3-1/samsung/hls_series_hdtv/index.html",
        "title": "HLS Series HDTVs",
        "count": 21,
        "level": 1,
        "sub": [
          {
            "url": "http://files.remotecentral.com/library/3-1/samsung/hls_series_hdtv/inputs/index.html",
            "title": "Inputs",
            "count": 10,
            "level": 2
          },
          {
            "url": "http://files.remotecentral.com/library/3-1/samsung/hls_series_hdtv/other_controls/index.html",
            "title": "Other Controls",
            "count": 2,
            "level": 2
          },
          {
            "url": "http://files.remotecentral.com/library/3-1/samsung/hls_series_hdtv/picture_modes/index.html",
            "title": "Picture Modes",
            "count": 3,
            "level": 2
          },
          {
            "url": "http://files.remotecentral.com/library/3-1/samsung/hls_series_hdtv/power_control/index.html",
            "title": "Power Control",
            "count": 2,
            "level": 2
          },
          {
            "url": "http://files.remotecentral.com/library/3-1/samsung/hls_series_hdtv/screen_formats/index.html",
            "title": "Screen Formats",
            "count": 4,
            "level": 2
          }
        ]
      },
      {
        "url": "http://files.remotecentral.com/library/3-1/samsung/hlt_series_hdtv/index.html",
        "title": "HLT Series HDTVs",
        "count": 21,
        "level": 1,
        "sub": [
          {
            "url": "http://files.remotecentral.com/library/3-1/samsung/hlt_series_hdtv/inputs/index.html",
            "title": "Inputs",
            "count": 13,
            "level": 2
          },
          {
            "url": "http://files.remotecentral.com/library/3-1/samsung/hlt_series_hdtv/others/index.html",
            "title": "Others",
            "count": 2,
            "level": 2
          },
          {
            "url": "http://files.remotecentral.com/library/3-1/samsung/hlt_series_hdtv/power_control/index.html",
            "title": "Power Control",
            "count": 1,
            "level": 2
          },
          {
            "url": "http://files.remotecentral.com/library/3-1/samsung/hlt_series_hdtv/screen_formats/index.html",
            "title": "Screen Formats",
            "count": 5,
            "level": 2
          }
        ]
      }
    ]
  },
  {
    "url": "http://files.remotecentral.com/library/3-1/sanyo/index.html",
    "title": "Sanyo",
    "count": 2,
    "level": 0,
    "sub": []
  },
  {
    "url": "http://files.remotecentral.com/library/3-1/sharp/index.html",
    "title": "Sharp",
    "count": 64,
    "level": 0,
    "sub": [
      {
        "url": "http://files.remotecentral.com/library/3-1/sharp/lcd_television/index.html",
        "title": "LCD Televisions",
        "count": 15,
        "level": 1,
        "sub": [
          {
            "url": "http://files.remotecentral.com/library/3-1/sharp/lcd_television/d92_series/index.html",
            "title": "D92 Series",
            "count": 7,
            "level": 2
          },
          {
            "url": "http://files.remotecentral.com/library/3-1/sharp/lcd_television/generic/index.html",
            "title": "Generic",
            "count": 6,
            "level": 2
          },
          {
            "url": "http://files.remotecentral.com/library/3-1/sharp/lcd_television/power_control/index.html",
            "title": "Power Control",
            "count": 2,
            "level": 2
          }
        ]
      },
      {
        "url": "http://files.remotecentral.com/library/3-1/sharp/projector/index.html",
        "title": "Projectors",
        "count": 6,
        "level": 1,
        "sub": [
          {
            "url": "http://files.remotecentral.com/library/3-1/sharp/projector/inputs/index.html",
            "title": "Inputs",
            "count": 4,
            "level": 2
          },
          {
            "url": "http://files.remotecentral.com/library/3-1/sharp/projector/power_control/index.html",
            "title": "Power Control",
            "count": 2,
            "level": 2
          }
        ]
      },
      {
        "url": "http://files.remotecentral.com/library/3-1/sharp/rp_television/index.html",
        "title": "RP Televisions",
        "count": 18,
        "level": 1,
        "sub": [
          {
            "url": "http://files.remotecentral.com/library/3-1/sharp/rp_television/inputs/index.html",
            "title": "Inputs",
            "count": 7,
            "level": 2
          },
          {
            "url": "http://files.remotecentral.com/library/3-1/sharp/rp_television/other/index.html",
            "title": "Other",
            "count": 5,
            "level": 2
          },
          {
            "url": "http://files.remotecentral.com/library/3-1/sharp/rp_television/power_control/index.html",
            "title": "Power Control",
            "count": 2,
            "level": 2
          },
          {
            "url": "http://files.remotecentral.com/library/3-1/sharp/rp_television/screen_formats/index.html",
            "title": "Screen Formats",
            "count": 4,
            "level": 2
          }
        ]
      },
      {
        "url": "http://files.remotecentral.com/library/3-1/sharp/sound_bar/index.html",
        "title": "Sound Bars",
        "count": 18,
        "level": 1,
        "sub": [
          {
            "url": "http://files.remotecentral.com/library/3-1/sharp/sound_bar/audio_control/index.html",
            "title": "Audio Control",
            "count": 1,
            "level": 2
          },
          {
            "url": "http://files.remotecentral.com/library/3-1/sharp/sound_bar/input_control/index.html",
            "title": "Input Control",
            "count": 4,
            "level": 2
          },
          {
            "url": "http://files.remotecentral.com/library/3-1/sharp/sound_bar/power_control/index.html",
            "title": "Power Control",
            "count": 1,
            "level": 2
          },
          {
            "url": "http://files.remotecentral.com/library/3-1/sharp/sound_bar/sound_format/index.html",
            "title": "Sound Format",
            "count": 8,
            "level": 2
          },
          {
            "url": "http://files.remotecentral.com/library/3-1/sharp/sound_bar/volume_control/index.html",
            "title": "Volume Control",
            "count": 3,
            "level": 2
          }
        ]
      },
      {
        "url": "http://files.remotecentral.com/library/3-1/sharp/television/index.html",
        "title": "Televisions",
        "count": 7,
        "level": 1,
        "sub": []
      }
    ]
  },
  {
    "url": "http://files.remotecentral.com/library/3-1/sonos/index.html",
    "title": "Sonos",
    "count": 4,
    "level": 0,
    "sub": []
  },
  {
    "url": "http://files.remotecentral.com/library/3-1/sony/index.html",
    "title": "Sony",
    "count": 200,
    "level": 0,
    "sub": [
      {
        "url": "http://files.remotecentral.com/library/3-1/sony/active_speaker/index.html",
        "title": "Active Speakers",
        "count": 2,
        "level": 1,
        "sub": []
      },
      {
        "url": "http://files.remotecentral.com/library/3-1/sony/amplifier/index.html",
        "title": "Amplifiers",
        "count": 5,
        "level": 1,
        "sub": []
      },
      {
        "url": "http://files.remotecentral.com/library/3-1/sony/blu-ray_player/index.html",
        "title": "Blu-ray Players",
        "count": 2,
        "level": 1,
        "sub": []
      },
      {
        "url": "http://files.remotecentral.com/library/3-1/sony/cd_jukebox/index.html",
        "title": "CD Jukeboxes",
        "count": 6,
        "level": 1,
        "sub": [
          {
            "url": "http://files.remotecentral.com/library/3-1/sony/cd_jukebox/code_1/index.html",
            "title": "Code 1",
            "count": 2,
            "level": 2
          },
          {
            "url": "http://files.remotecentral.com/library/3-1/sony/cd_jukebox/code_2/index.html",
            "title": "Code 2",
            "count": 2,
            "level": 2
          },
          {
            "url": "http://files.remotecentral.com/library/3-1/sony/cd_jukebox/code_3/index.html",
            "title": "Code 3",
            "count": 2,
            "level": 2
          }
        ]
      },
      {
        "url": "http://files.remotecentral.com/library/3-1/sony/dat_deck/index.html",
        "title": "DAT Decks",
        "count": 2,
        "level": 1,
        "sub": []
      },
      {
        "url": "http://files.remotecentral.com/library/3-1/sony/dss_receiver/index.html",
        "title": "DSS Receivers",
        "count": 6,
        "level": 1,
        "sub": [
          {
            "url": "http://files.remotecentral.com/library/3-1/sony/dss_receiver/code_51/index.html",
            "title": "Code 51",
            "count": 2,
            "level": 2
          },
          {
            "url": "http://files.remotecentral.com/library/3-1/sony/dss_receiver/normal__50/index.html",
            "title": "Normal/50",
            "count": 2,
            "level": 2
          }
        ]
      },
      {
        "url": "http://files.remotecentral.com/library/3-1/sony/dtt_receiver/index.html",
        "title": "DTT Receivers",
        "count": 2,
        "level": 1,
        "sub": []
      },
      {
        "url": "http://files.remotecentral.com/library/3-1/sony/dvd_player/index.html",
        "title": "DVD Players",
        "count": 6,
        "level": 1,
        "sub": [
          {
            "url": "http://files.remotecentral.com/library/3-1/sony/dvd_player/code_1/index.html",
            "title": "Code 1",
            "count": 2,
            "level": 2
          },
          {
            "url": "http://files.remotecentral.com/library/3-1/sony/dvd_player/code_2/index.html",
            "title": "Code 2",
            "count": 2,
            "level": 2
          },
          {
            "url": "http://files.remotecentral.com/library/3-1/sony/dvd_player/code_3/index.html",
            "title": "Code 3",
            "count": 2,
            "level": 2
          }
        ]
      },
      {
        "url": "http://files.remotecentral.com/library/3-1/sony/dvd_recorder/index.html",
        "title": "DVD Recorders",
        "count": 16,
        "level": 1,
        "sub": [
          {
            "url": "http://files.remotecentral.com/library/3-1/sony/dvd_recorder/code_1/index.html",
            "title": "Code 1",
            "count": 5,
            "level": 2
          },
          {
            "url": "http://files.remotecentral.com/library/3-1/sony/dvd_recorder/code_2/index.html",
            "title": "Code 2",
            "count": 5,
            "level": 2
          },
          {
            "url": "http://files.remotecentral.com/library/3-1/sony/dvd_recorder/code_3/index.html",
            "title": "Code 3",
            "count": 6,
            "level": 2
          }
        ]
      },
      {
        "url": "http://files.remotecentral.com/library/3-1/sony/dvd_recorder__vcr/index.html",
        "title": "DVD Recorder/VCRs",
        "count": 6,
        "level": 1,
        "sub": [
          {
            "url": "http://files.remotecentral.com/library/3-1/sony/dvd_recorder__vcr/code_1/index.html",
            "title": "Code 1",
            "count": 2,
            "level": 2
          },
          {
            "url": "http://files.remotecentral.com/library/3-1/sony/dvd_recorder__vcr/code_2/index.html",
            "title": "Code 2",
            "count": 2,
            "level": 2
          },
          {
            "url": "http://files.remotecentral.com/library/3-1/sony/dvd_recorder__vcr/code_3/index.html",
            "title": "Code 3",
            "count": 2,
            "level": 2
          }
        ]
      },
      {
        "url": "http://files.remotecentral.com/library/3-1/sony/hdtv_dvr/index.html",
        "title": "HDTV DVRs",
        "count": 8,
        "level": 1,
        "sub": [
          {
            "url": "http://files.remotecentral.com/library/3-1/sony/hdtv_dvr/australian_(code_1)/index.html",
            "title": "Australian (Code 1)",
            "count": 2,
            "level": 2
          },
          {
            "url": "http://files.remotecentral.com/library/3-1/sony/hdtv_dvr/code_50/index.html",
            "title": "Code 50",
            "count": 3,
            "level": 2
          },
          {
            "url": "http://files.remotecentral.com/library/3-1/sony/hdtv_dvr/code_51/index.html",
            "title": "Code 51",
            "count": 3,
            "level": 2
          }
        ]
      },
      {
        "url": "http://files.remotecentral.com/library/3-1/sony/home_theater_system/index.html",
        "title": "Home Theater Systems",
        "count": 6,
        "level": 1,
        "sub": [
          {
            "url": "http://files.remotecentral.com/library/3-1/sony/home_theater_system/inputs/index.html",
            "title": "Inputs",
            "count": 4,
            "level": 2
          },
          {
            "url": "http://files.remotecentral.com/library/3-1/sony/home_theater_system/power_control/index.html",
            "title": "Power Control",
            "count": 2,
            "level": 2
          }
        ]
      },
      {
        "url": "http://files.remotecentral.com/library/3-1/sony/laserdisc_player/index.html",
        "title": "LaserDisc Players",
        "count": 2,
        "level": 1,
        "sub": []
      },
      {
        "url": "http://files.remotecentral.com/library/3-1/sony/lcd_(2010)_television/index.html",
        "title": "LCD (2010) Televisions",
        "count": 16,
        "level": 1,
        "sub": [
          {
            "url": "http://files.remotecentral.com/library/3-1/sony/lcd_(2010)_television/inputs/index.html",
            "title": "Inputs",
            "count": 12,
            "level": 2
          },
          {
            "url": "http://files.remotecentral.com/library/3-1/sony/lcd_(2010)_television/other/index.html",
            "title": "Other",
            "count": 2,
            "level": 2
          },
          {
            "url": "http://files.remotecentral.com/library/3-1/sony/lcd_(2010)_television/power_control/index.html",
            "title": "Power Control",
            "count": 2,
            "level": 2
          }
        ]
      },
      {
        "url": "http://files.remotecentral.com/library/3-1/sony/minidisc_deck/index.html",
        "title": "MiniDisc Decks",
        "count": 2,
        "level": 1,
        "sub": []
      },
      {
        "url": "http://files.remotecentral.com/library/3-1/sony/mp3_jukebox/index.html",
        "title": "MP3 Jukeboxes",
        "count": 2,
        "level": 1,
        "sub": []
      },
      {
        "url": "http://files.remotecentral.com/library/3-1/sony/plasma_display/index.html",
        "title": "Plasma Displays",
        "count": 10,
        "level": 1,
        "sub": [
          {
            "url": "http://files.remotecentral.com/library/3-1/sony/plasma_display/inputs/index.html",
            "title": "Inputs",
            "count": 8,
            "level": 2
          },
          {
            "url": "http://files.remotecentral.com/library/3-1/sony/plasma_display/power_control/index.html",
            "title": "Power Control",
            "count": 2,
            "level": 2
          }
        ]
      },
      {
        "url": "http://files.remotecentral.com/library/3-1/sony/preamplifier/index.html",
        "title": "Preamplifiers",
        "count": 2,
        "level": 1,
        "sub": []
      },
      {
        "url": "http://files.remotecentral.com/library/3-1/sony/projector/index.html",
        "title": "Projectors",
        "count": 9,
        "level": 1,
        "sub": [
          {
            "url": "http://files.remotecentral.com/library/3-1/sony/projector/inputs/index.html",
            "title": "Inputs",
            "count": 6,
            "level": 2
          },
          {
            "url": "http://files.remotecentral.com/library/3-1/sony/projector/other/index.html",
            "title": "Other",
            "count": 1,
            "level": 2
          },
          {
            "url": "http://files.remotecentral.com/library/3-1/sony/projector/power_control/index.html",
            "title": "Power Control",
            "count": 2,
            "level": 2
          }
        ]
      },
      {
        "url": "http://files.remotecentral.com/library/3-1/sony/receiver/index.html",
        "title": "Receivers",
        "count": 8,
        "level": 1,
        "sub": [
          {
            "url": "http://files.remotecentral.com/library/3-1/sony/receiver/av1_(older__alternate)/index.html",
            "title": "AV1 (Older/Alternate)",
            "count": 4,
            "level": 2
          },
          {
            "url": "http://files.remotecentral.com/library/3-1/sony/receiver/av2_(current)/index.html",
            "title": "AV2 (Current)",
            "count": 4,
            "level": 2
          }
        ]
      },
      {
        "url": "http://files.remotecentral.com/library/3-1/sony/television/index.html",
        "title": "Televisions",
        "count": 51,
        "level": 1,
        "sub": [
          {
            "url": "http://files.remotecentral.com/library/3-1/sony/television/audio_controls/index.html",
            "title": "Audio Controls",
            "count": 7,
            "level": 2
          },
          {
            "url": "http://files.remotecentral.com/library/3-1/sony/television/inputs/index.html",
            "title": "Inputs",
            "count": 13,
            "level": 2
          },
          {
            "url": "http://files.remotecentral.com/library/3-1/sony/television/inputs_(alternate)/index.html",
            "title": "Inputs (Alternate)",
            "count": 6,
            "level": 2
          },
          {
            "url": "http://files.remotecentral.com/library/3-1/sony/television/other/index.html",
            "title": "Other",
            "count": 5,
            "level": 2
          },
          {
            "url": "http://files.remotecentral.com/library/3-1/sony/television/power_control/index.html",
            "title": "Power Control",
            "count": 4,
            "level": 2
          },
          {
            "url": "http://files.remotecentral.com/library/3-1/sony/television/screen_formats/index.html",
            "title": "Screen Formats",
            "count": 5,
            "level": 2
          },
          {
            "url": "http://files.remotecentral.com/library/3-1/sony/television/video_controls/index.html",
            "title": "Video Controls",
            "count": 11,
            "level": 2
          }
        ]
      },
      {
        "url": "http://files.remotecentral.com/library/3-1/sony/uhd_player/index.html",
        "title": "UHD Players",
        "count": 2,
        "level": 1,
        "sub": []
      },
      {
        "url": "http://files.remotecentral.com/library/3-1/sony/vcr/index.html",
        "title": "VCRs",
        "count": 26,
        "level": 1,
        "sub": [
          {
            "url": "http://files.remotecentral.com/library/3-1/sony/vcr/vtr1__beta/index.html",
            "title": "VTR1/Beta",
            "count": 9,
            "level": 2
          },
          {
            "url": "http://files.remotecentral.com/library/3-1/sony/vcr/vtr2__8mm/index.html",
            "title": "VTR2/8mm",
            "count": 8,
            "level": 2
          },
          {
            "url": "http://files.remotecentral.com/library/3-1/sony/vcr/vtr3__vhs/index.html",
            "title": "VTR3/VHS",
            "count": 9,
            "level": 2
          }
        ]
      },
      {
        "url": "http://files.remotecentral.com/library/3-1/sony/webtv/index.html",
        "title": "WebTVs",
        "count": 2,
        "level": 1,
        "sub": []
      },
      {
        "url": "http://files.remotecentral.com/library/3-1/sony/whole_system/index.html",
        "title": "Whole Systems",
        "count": 1,
        "level": 1,
        "sub": []
      }
    ]
  },
  {
    "url": "http://files.remotecentral.com/library/3-1/t%252Ba/index.html",
    "title": "T+A",
    "count": 48,
    "level": 0,
    "sub": [
      {
        "url": "http://files.remotecentral.com/library/3-1/t%252Ba/whole_system/index.html",
        "title": "Whole Systems",
        "count": 48,
        "level": 1,
        "sub": [
          {
            "url": "http://files.remotecentral.com/library/3-1/t%252Ba/whole_system/audio_control/index.html",
            "title": "Audio Control",
            "count": 18,
            "level": 2
          },
          {
            "url": "http://files.remotecentral.com/library/3-1/t%252Ba/whole_system/inputs/index.html",
            "title": "Inputs",
            "count": 15,
            "level": 2
          },
          {
            "url": "http://files.remotecentral.com/library/3-1/t%252Ba/whole_system/other/index.html",
            "title": "Other",
            "count": 8,
            "level": 2
          },
          {
            "url": "http://files.remotecentral.com/library/3-1/t%252Ba/whole_system/power_control/index.html",
            "title": "Power Control",
            "count": 7,
            "level": 2
          }
        ]
      }
    ]
  },
  {
    "url": "http://files.remotecentral.com/library/3-1/technics/index.html",
    "title": "Technics",
    "count": 6,
    "level": 0,
    "sub": [
      {
        "url": "http://files.remotecentral.com/library/3-1/technics/cd_player/index.html",
        "title": "CD Players",
        "count": 2,
        "level": 1,
        "sub": []
      },
      {
        "url": "http://files.remotecentral.com/library/3-1/technics/dsp/index.html",
        "title": "DSPs",
        "count": 2,
        "level": 1,
        "sub": []
      },
      {
        "url": "http://files.remotecentral.com/library/3-1/technics/receiver/index.html",
        "title": "Receivers",
        "count": 2,
        "level": 1,
        "sub": []
      }
    ]
  },
  {
    "url": "http://files.remotecentral.com/library/3-1/tevion/index.html",
    "title": "Tevion",
    "count": 2,
    "level": 0,
    "sub": []
  },
  {
    "url": "http://files.remotecentral.com/library/3-1/thomson/index.html",
    "title": "Thomson",
    "count": 2,
    "level": 0,
    "sub": []
  },
  {
    "url": "http://files.remotecentral.com/library/3-1/tivo/index.html",
    "title": "TiVo",
    "count": 10,
    "level": 0,
    "sub": []
  },
  {
    "url": "http://files.remotecentral.com/library/3-1/topfield/index.html",
    "title": "Topfield",
    "count": 1,
    "level": 0,
    "sub": []
  },
  {
    "url": "http://files.remotecentral.com/library/3-1/toshiba/index.html",
    "title": "Toshiba",
    "count": 8,
    "level": 0,
    "sub": [
      {
        "url": "http://files.remotecentral.com/library/3-1/toshiba/hd-dvd_player/index.html",
        "title": "HD-DVD Players",
        "count": 6,
        "level": 1,
        "sub": [
          {
            "url": "http://files.remotecentral.com/library/3-1/toshiba/hd-dvd_player/other/index.html",
            "title": "Other",
            "count": 3,
            "level": 2
          },
          {
            "url": "http://files.remotecentral.com/library/3-1/toshiba/hd-dvd_player/power_control/index.html",
            "title": "Power Control",
            "count": 3,
            "level": 2
          }
        ]
      },
      {
        "url": "http://files.remotecentral.com/library/3-1/toshiba/rp_television/index.html",
        "title": "RP Televisions",
        "count": 2,
        "level": 1,
        "sub": []
      }
    ]
  },
  {
    "url": "http://files.remotecentral.com/library/3-1/turtle_beach/index.html",
    "title": "Turtle Beach",
    "count": 2,
    "level": 0,
    "sub": []
  },
  {
    "url": "http://files.remotecentral.com/library/3-1/tvix/index.html",
    "title": "TViX",
    "count": 2,
    "level": 0,
    "sub": []
  },
  {
    "url": "http://files.remotecentral.com/library/3-1/viewsonic/index.html",
    "title": "Viewsonic",
    "count": 6,
    "level": 0,
    "sub": [
      {
        "url": "http://files.remotecentral.com/library/3-1/viewsonic/lcd_television/index.html",
        "title": "LCD Televisions",
        "count": 6,
        "level": 1,
        "sub": [
          {
            "url": "http://files.remotecentral.com/library/3-1/viewsonic/lcd_television/inputs/index.html",
            "title": "Inputs",
            "count": 4,
            "level": 2
          },
          {
            "url": "http://files.remotecentral.com/library/3-1/viewsonic/lcd_television/power_control/index.html",
            "title": "Power Control",
            "count": 2,
            "level": 2
          }
        ]
      }
    ]
  },
  {
    "url": "http://files.remotecentral.com/library/3-1/vu%252B/index.html",
    "title": "Vu+",
    "count": 2,
    "level": 0,
    "sub": []
  },
  {
    "url": "http://files.remotecentral.com/library/3-1/wharfdale/index.html",
    "title": "Wharfdale",
    "count": 4,
    "level": 0,
    "sub": []
  },
  {
    "url": "http://files.remotecentral.com/library/3-1/yamaha/index.html",
    "title": "Yamaha",
    "count": 7,
    "level": 0,
    "sub": [
      {
        "url": "http://files.remotecentral.com/library/3-1/yamaha/dvd_player/index.html",
        "title": "DVD Players",
        "count": 2,
        "level": 1,
        "sub": []
      },
      {
        "url": "http://files.remotecentral.com/library/3-1/yamaha/receiver/index.html",
        "title": "Receivers",
        "count": 5,
        "level": 1,
        "sub": []
      }
    ]
  },
  {
    "url": "http://files.remotecentral.com/library/3-1/zeevee/index.html",
    "title": "ZeeVee",
    "count": 3,
    "level": 0,
    "sub": []
  },
  {
    "url": "http://files.remotecentral.com/library/3-1/zenith/index.html",
    "title": "Zenith",
    "count": 20,
    "level": 0,
    "sub": [
      {
        "url": "http://files.remotecentral.com/library/3-1/zenith/cable_box/index.html",
        "title": "Cable Boxes",
        "count": 4,
        "level": 1,
        "sub": []
      },
      {
        "url": "http://files.remotecentral.com/library/3-1/zenith/hdtv_receiver/index.html",
        "title": "HDTV Receivers",
        "count": 4,
        "level": 1,
        "sub": [
          {
            "url": "http://files.remotecentral.com/library/3-1/zenith/hdtv_receiver/dtt901/index.html",
            "title": "DTT901",
            "count": 1,
            "level": 2
          },
          {
            "url": "http://files.remotecentral.com/library/3-1/zenith/hdtv_receiver/other_models/index.html",
            "title": "Other Models",
            "count": 3,
            "level": 2
          }
        ]
      },
      {
        "url": "http://files.remotecentral.com/library/3-1/zenith/plasma_display/index.html",
        "title": "Plasma Displays",
        "count": 9,
        "level": 1,
        "sub": [
          {
            "url": "http://files.remotecentral.com/library/3-1/zenith/plasma_display/inputs/index.html",
            "title": "Inputs",
            "count": 5,
            "level": 2
          },
          {
            "url": "http://files.remotecentral.com/library/3-1/zenith/plasma_display/power_control/index.html",
            "title": "Power Control",
            "count": 2,
            "level": 2
          },
          {
            "url": "http://files.remotecentral.com/library/3-1/zenith/plasma_display/screen_formats/index.html",
            "title": "Screen Formats",
            "count": 2,
            "level": 2
          }
        ]
      },
      {
        "url": "http://files.remotecentral.com/library/3-1/zenith/vcr/index.html",
        "title": "VCRs",
        "count": 3,
        "level": 1,
        "sub": []
      }
    ]
  },
  {
    "url": "http://files.remotecentral.com/library/3-1/zvox/index.html",
    "title": "ZVOX",
    "count": 7,
    "level": 0,
    "sub": [
      {
        "url": "http://files.remotecentral.com/library/3-1/zvox/sound_bar/index.html",
        "title": "Sound Bars",
        "count": 7,
        "level": 1,
        "sub": [
          {
            "url": "http://files.remotecentral.com/library/3-1/zvox/sound_bar/inputs/index.html",
            "title": "Inputs",
            "count": 5,
            "level": 2
          },
          {
            "url": "http://files.remotecentral.com/library/3-1/zvox/sound_bar/power/index.html",
            "title": "Power",
            "count": 2,
            "level": 2
          }
        ]
      }
    ]
  }
]